HISTORY.rst
MANIFEST.in
README.rst
setup.cfg
setup.py
versioneer.py
pyutrack/__init__.py
pyutrack/_version.py
pyutrack/config.py
pyutrack/connection.py
pyutrack/errors.py
pyutrack/logger.py
pyutrack/resources.py
pyutrack/templating.py
pyutrack/util.py
pyutrack/version.py
pyutrack.egg-info/PKG-INFO
pyutrack.egg-info/SOURCES.txt
pyutrack.egg-info/dependency_links.txt
pyutrack.egg-info/entry_points.txt
pyutrack.egg-info/not-zip-safe
pyutrack.egg-info/requires.txt
pyutrack.egg-info/top_level.txt
pyutrack/cli/__init__.py
pyutrack/cli/__main__.py
pyutrack/cli/debug.py
pyutrack/cli/delete.py
pyutrack/cli/list.py
pyutrack/cli/new.py
pyutrack/cli/show.py
pyutrack/cli/update.py
pyutrack/cli/util.py
requirements/ci.txt
requirements/dev.txt
requirements/docs.txt
requirements/main.txt
requirements/setup.txt
requirements/test.txt
tests/integration/__init__.py
tests/integration/test_authentication.py