Metadata-Version: 1.1
Name: pyutrack
Version: 0.7.1
Summary: Command line utility to interface with YouTrack
Home-page: https://github.com/alisaifee/pyutrack
Author: Ali-Akber Saifee
Author-email: ali@indydevs.org
License: MIT license
Keywords: pyutrack
Platform: UNKNOWN
Classifier: Development Status :: 2 - Pre-Alpha
Classifier: Intended Audience :: Developers
Classifier: License :: OSI Approved :: MIT License
Classifier: Natural Language :: English
Classifier: Programming Language :: Python :: 2
Classifier: Programming Language :: Python :: 2.6
Classifier: Programming Language :: Python :: 2.7
Classifier: Programming Language :: Python :: 3
Classifier: Programming Language :: Python :: 3.3
Classifier: Programming Language :: Python :: 3.4
Classifier: Programming Language :: Python :: 3.5
